ape/Snakefile
ape/Snakefile~
ape/__init__.py
ape/ape.py
ape/ape.py~
gi_ape-1.0.dist-info/DESCRIPTION.rst
gi_ape-1.0.dist-info/METADATA
gi_ape-1.0.dist-info/RECORD
gi_ape-1.0.dist-info/WHEEL
gi_ape-1.0.dist-info/entry_points.txt
gi_ape-1.0.dist-info/metadata.json
gi_ape-1.0.dist-info/top_level.txt
