Metadata-Version: 2.0
Name: gi-ape
Version: 1.0
Summary: UNKNOWN
Home-page: https://bitbucket.org/christopherschroeder/ape
Author: Christopher Schröder and Sven Rahmann
Author-email: christopher.schroeder@tu-dortmund.de
License: MIT
Platform: UNKNOWN
Classifier: Topic :: Scientific/Engineering :: Bio-Informatics
Classifier: Framework :: Flask
Classifier: Environment :: Web Environment
Classifier: Intended Audience :: Science/Research
Requires-Dist: numpy
Requires-Dist: pysam
Requires-Dist: snakemake
